explay/__init__.py
explay/__main__.py
explay/agg_func.py
explay/exp.py
explay/merger.py
explay/openpyxl_ext.py
explay/parser.py
explay/post_func.py
explay/source.py
explay/utils.py
explay-0.6.1.dist-info/METADATA
explay-0.6.1.dist-info/WHEEL
explay-0.6.1.dist-info/entry_points.txt
explay-0.6.1.dist-info/top_level.txt
explay-0.6.1.dist-info/RECORD
